{
    "_links": {
        "self": {
            "href": "http:\/\/default\/taxonomy\/term\/13?_format=hal_json"
        },
        "type": {
            "href": "http:\/\/drupal.org\/rest\/type\/taxonomy_term\/soil_type"
        }
    },
    "tid": [
        {
            "value": "13"
        }
    ],
    "uuid": [
        {
            "value": "01dee834-6cc0-4bd3-b12c-185aede4f3cf"
        }
    ],
    "langcode": [
        {
            "value": "en",
            "lang": "en"
        }
    ],
    "vid": [
        {
            "target_id": "soil_type"
        }
    ],
    "name": [
        {
            "value": "Loam",
            "lang": "en"
        }
    ],
    "weight": [
        {
            "value": "0"
        }
    ],
    "changed": [
        {
            "value": "1481130846",
            "lang": "en"
        }
    ],
    "default_langcode": [
        {
            "value": "1",
            "lang": "en"
        }
    ]
}